cndprint/VERSION
cndprint/__init__.py
cndprint/__version__.py
cndprint/cnd_print.py
cndprint-0.1.2.dist-info/METADATA
cndprint-0.1.2.dist-info/WHEEL
cndprint-0.1.2.dist-info/top_level.txt
cndprint-0.1.2.dist-info/RECORD
