Metadata-Version: 2.1
Name: cndprint
Version: 0.1.2
Summary: The definitive tools to print pretty error log message
Home-page: https://changendevops.com
Author: Denis FABIEN
Author-email: denis.fabien@changendevops.com
License: MIT/X11
Project-URL: Documentation, https://changendevops.com
Project-URL: Source, https://gitlab.com/changendevops/cndversion
Classifier: License :: OSI Approved :: MIT License
Classifier: Operating System :: OS Independent
